eventchain/__init__.py
eventchain/_modidx.py
eventchain/core.py
eventchain-0.0.3.dist-info/LICENSE
eventchain-0.0.3.dist-info/METADATA
eventchain-0.0.3.dist-info/WHEEL
eventchain-0.0.3.dist-info/entry_points.txt
eventchain-0.0.3.dist-info/top_level.txt
eventchain-0.0.3.dist-info/RECORD
