Metadata-Version: 2.1
Name: eventchain
Version: 0.0.3
Summary: Simplified Chain Analytics
Home-page: https://github.com/tkanngiesser/eventchain
Author: tkanngiesser
Author-email: tinokanngiesser@gmail.com
License: Apache Software License 2.0
Keywords: nbdev jupyter notebook python
Classifier: Development Status :: 4 - Beta
Classifier: Intended Audience :: Developers
Classifier: Natural Language :: English
Classifier: Programming Language :: Python :: 3.7
Classifier: Programming Language :: Python :: 3.8
Classifier: Programming Language :: Python :: 3.9
Classifier: Programming Language :: Python :: 3.10
Classifier: License :: OSI Approved :: Apache Software License
Requires-Python: >=3.7
License-File: LICENSE
Requires-Dist: pandas
Requires-Dist: scipy
Provides-Extra: dev
